fastapi_mailman/__init__.py
fastapi_mailman/backends/__init__.py
fastapi_mailman/backends/base.py
fastapi_mailman/backends/console.py
fastapi_mailman/backends/dummy.py
fastapi_mailman/backends/file.py
fastapi_mailman/backends/locmem.py
fastapi_mailman/backends/smtp.py
fastapi_mailman/config.py
fastapi_mailman/errors.py
fastapi_mailman/globals.py
fastapi_mailman/message.py
fastapi_mailman/utils.py
fastapi_mailman-0.0.3.dist-info/LICENSE
fastapi_mailman-0.0.3.dist-info/WHEEL
fastapi_mailman-0.0.3.dist-info/METADATA
fastapi_mailman-0.0.3.dist-info/RECORD
