Metadata-Version: 2.1
Name: fastapi-mailman
Version: 0.0.3
Summary: Porting Django's email implementation to your FastAPI applications.
Home-page: https://github.com/marktennyson/fastapi-mailman
License: MIT
Keywords: fastapi,mail,smtp,fastapi-mail
Author: Aniket Sarkar
Author-email: aniketsarkar@yahoo.com
Requires-Python: >=3.6.2,<4.0.0
Classifier: Development Status :: 4 - Beta
Classifier: Intended Audience :: Developers
Classifier: License :: OSI Approved :: GNU General Public License v3 or later (GPLv3+)
Classifier: License :: OSI Approved :: MIT License
Classifier: Programming Language :: Python :: 3
Classifier: Programming Language :: Python :: 3.10
Classifier: Programming Language :: Python :: 3.6
Classifier: Programming Language :: Python :: 3.7
Classifier: Programming Language :: Python :: 3.8
Classifier: Programming Language :: Python :: 3.9
Classifier: Topic :: Communications :: Email
Classifier: Topic :: Software Development :: Build Tools
Provides-Extra: dev
Provides-Extra: doc
Provides-Extra: test
Requires-Dist: Jinja2 (>=3.0.1,<4.0.0)
Requires-Dist: aiosmtplib (>=1.1.6,<2.0.0)
Requires-Dist: anyio (>=3.3.2,<4.0.0); extra == "test"
Requires-Dist: black (>=21.5b2,<22.0); extra == "test"
Requires-Dist: bump2version (>=1.0.1,<2.0.0); extra == "dev"
Requires-Dist: dnspython (>=2.1.0,<3.0.0)
Requires-Dist: email-validator (>=1.1.3,<2.0.0)
Requires-Dist: fastapi (>=0.68.1,<0.69.0)
Requires-Dist: flake8 (>=3.9.2,<4.0.0); extra == "test"
Requires-Dist: isort (>=5.8.0,<6.0.0); extra == "test"
Requires-Dist: mkdocs (>=1.1.2,<2.0.0); extra == "doc"
Requires-Dist: mkdocs-autorefs (>=0.2.1,<0.3.0); extra == "doc"
Requires-Dist: mkdocs-include-markdown-plugin (>=1.0.0,<2.0.0); extra == "doc"
Requires-Dist: mkdocs-material (>=6.1.7,<7.0.0); extra == "doc"
Requires-Dist: mkdocs-material-extensions (>=1.0.1,<2.0.0); extra == "doc"
Requires-Dist: mkdocstrings (>=0.15.2,<0.16.0); extra == "doc"
Requires-Dist: pip (>=21.1,<22.0); extra == "dev"
Requires-Dist: pre-commit (>=2.12.0,<3.0.0); extra == "dev"
Requires-Dist: pydantic (>=1.8.2,<2.0.0)
Requires-Dist: pytest (>=6.2.4,<7.0.0); extra == "test"
Requires-Dist: pytest-cov (>=2.12.0,<3.0.0); extra == "test"
Requires-Dist: toml (>=0.10.2,<0.11.0); extra == "dev"
Requires-Dist: tox (>=3.20.1,<4.0.0); extra == "dev"
Requires-Dist: trio (>=0.19.0,<0.20.0); extra == "test"
Requires-Dist: twine (>=3.3.0,<4.0.0); extra == "dev"
Requires-Dist: virtualenv (>=20.2.2,<21.0.0); extra == "dev"
Project-URL: Repository, https://github.com/marktennyson/fastapi-mailman
